pycmpp
